README.md
setup.py
erazhan_utils/__init__.py
erazhan_utils/conn_pg.py
erazhan_utils/constants.py
erazhan_utils/decorator_utils.py
erazhan_utils/json_utils.py
erazhan_utils/judge_utils.py
erazhan_utils/logging_utils.py
erazhan_utils/math_utils.py
erazhan_utils/os_utils.py
erazhan_utils/re_utils.py
erazhan_utils/sklearn_utils.py
erazhan_utils/special_utils.py
erazhan_utils/test.py
erazhan_utils/time_utils.py
erazhan_utils/trie_tree.py
erazhan_utils.egg-info/PKG-INFO
erazhan_utils.egg-info/SOURCES.txt
erazhan_utils.egg-info/dependency_links.txt
erazhan_utils.egg-info/requires.txt
erazhan_utils.egg-info/top_level.txt