Metadata-Version: 2.4
Name: erazhan_utils
Version: 0.0.15
Summary: some common tools in work
Home-page: https://github.com/erazhan/erazhan_utils
Author: erazhan
Author-email: erazhan@163.com
License: MIT Licence
Keywords: erazhan_utils
Platform: any
Requires-Python: >=3.6.1
Requires-Dist: numpy
Dynamic: author
Dynamic: author-email
Dynamic: description
Dynamic: home-page
Dynamic: keywords
Dynamic: license
Dynamic: platform
Dynamic: requires-dist
Dynamic: requires-python
Dynamic: summary
